mtrpacket/__init__.py
mtrpacket-1.0.0.dist-info/LICENSE
mtrpacket-1.0.0.dist-info/METADATA
mtrpacket-1.0.0.dist-info/WHEEL
mtrpacket-1.0.0.dist-info/top_level.txt
mtrpacket-1.0.0.dist-info/RECORD
