Metadata-Version: 2.1
Name: mtrpacket
Version: 1.0.0
Summary: Asynchronous network probes for Python
Home-page: https://github.com/matt-kimball/mtr-packet-python
Author: Matt Kimball
Author-email: matt.kimball@gmail.com
License: UNKNOWN
Platform: UNKNOWN
Classifier: Topic :: System :: Networking
Classifier: Framework :: AsyncIO
Classifier: Programming Language :: Python :: 3
Classifier: License :: OSI Approved :: MIT License
Requires-Python: >=3.5
